[{
    "name": "Stronger",
    "duration": "312",
    "playcount": "33",
    "mbid": "0d3cb71d-eba1-419b-950a-e7d780d6c8ba",
    "url": "http://www.last.fm/music/Kanye+West/_/Stronger",
    "streamable": {
        "#text": "0",
        "fulltrack": "0"
    },
    "artist": {
        "name": "Kanye West",
        "mbid": "164f0d73-1234-4e2c-8743-d77bf2191051",
        "url": "http://www.last.fm/music/Kanye+West"
    },
    "image": [
        {
            "#text": "http://userserve-ak.last.fm/serve/34s/88995171.png",
            "size": "small"
        },
        {
            "#text": "http://userserve-ak.last.fm/serve/64s/88995171.png",
            "size": "medium"
        },
        {
            "#text": "http://userserve-ak.last.fm/serve/126/88995171.png",
            "size": "large"
        },
        {
            "#text": "http://userserve-ak.last.fm/serve/300x300/88995171.png",
            "size": "extralarge"
        }
    ],
    "@attr": {
        "rank": "20"
    }
}, {
    "name": "Use Somebody",
    "duration": "231",
    "playcount": "13",
    "mbid": "02613fe2-c996-423d-a547-d2a786dff275",
    "url": "http://www.last.fm/music/Kings+of+Leon/_/Use+Somebody",
    "streamable": {
        "#text": "0",
        "fulltrack": "0"
    },
    "artist": {
        "name": "Kings of Leon",
        "mbid": "6ffb8ea9-2370-44d8-b678-e9237bbd347b",
        "url": "http://www.last.fm/music/Kings+of+Leon"
    },
    "image": [
        {
            "#text": "http://userserve-ak.last.fm/serve/34s/81102241.png",
            "size": "small"
        },
        {
            "#text": "http://userserve-ak.last.fm/serve/64s/81102241.png",
            "size": "medium"
        },
        {
            "#text": "http://userserve-ak.last.fm/serve/126/81102241.png",
            "size": "large"
        },
        {
            "#text": "http://userserve-ak.last.fm/serve/300x300/81102241.png",
            "size": "extralarge"
        }
    ],
    "@attr": {
        "rank": "83"
    }
}, {
    "name": "Creep",
    "duration": "235",
    "playcount": "17",
    "mbid": "02093751-b80e-4d20-8e9f-d502df6bf516",
    "url": "http://www.last.fm/music/Radiohead/_/Creep",
    "streamable": {
        "#text": "0",
        "fulltrack": "0"
    },
    "artist": {
        "name": "Radiohead",
        "mbid": "a74b1b7f-71a5-4011-9441-d0b5e4122711",
        "url": "http://www.last.fm/music/Radiohead"
    },
    "image": [
        {
            "#text": "http://userserve-ak.last.fm/serve/34s/49158523.png",
            "size": "small"
        },
        {
            "#text": "http://userserve-ak.last.fm/serve/64s/49158523.png",
            "size": "medium"
        },
        {
            "#text": "http://userserve-ak.last.fm/serve/126/49158523.png",
            "size": "large"
        },
        {
            "#text": "http://userserve-ak.last.fm/serve/300x300/49158523.png",
            "size": "extralarge"
        }
    ],
    "@attr": {
        "rank": "31"
    }
}, {
    "name": "Smells Like Teen Spirit",
    "duration": "300",
    "playcount": "16",
    "mbid": "b522c65f-4b63-4ff5-9d04-8627ab329e67",
    "url": "http://www.last.fm/music/Nirvana/_/Smells+Like+Teen+Spirit",
    "streamable": {
        "#text": "0",
        "fulltrack": "0"
    },
    "artist": {
        "name": "Nirvana",
        "mbid": "5b11f4ce-a62d-471e-81fc-a69a8278c7da",
        "url": "http://www.last.fm/music/Nirvana"
    },
    "image": [
        {
            "#text": "http://userserve-ak.last.fm/serve/34s/83456717.png",
            "size": "small"
        },
        {
            "#text": "http://userserve-ak.last.fm/serve/64s/83456717.png",
            "size": "medium"
        },
        {
            "#text": "http://userserve-ak.last.fm/serve/126/83456717.png",
            "size": "large"
        },
        {
            "#text": "http://userserve-ak.last.fm/serve/300x300/83456717.png",
            "size": "extralarge"
        }
    ],
    "@attr": {
        "rank": "36"
    }
}, {
    "name": "Bad Romance",
    "duration": "295",
    "playcount": "61",
    "mbid": "4643e7e3-7487-452f-93cc-5aa1b0829e50",
    "url": "http://www.last.fm/music/Lady+Gaga/_/Bad+Romance",
    "streamable": {
        "#text": "0",
        "fulltrack": "0"
    },
    "artist": {
        "name": "Lady Gaga",
        "mbid": "650e7db6-b795-4eb5-a702-5ea2fc46c848",
        "url": "http://www.last.fm/music/Lady+Gaga"
    },
    "image": [
        {
            "#text": "http://userserve-ak.last.fm/serve/34s/92841519.png",
            "size": "small"
        },
        {
            "#text": "http://userserve-ak.last.fm/serve/64s/92841519.png",
            "size": "medium"
        },
        {
            "#text": "http://userserve-ak.last.fm/serve/126/92841519.png",
            "size": "large"
        },
        {
            "#text": "http://userserve-ak.last.fm/serve/300x300/92841519.png",
            "size": "extralarge"
        }
    ],
    "@attr": {
        "rank": "18"
    }
}, {
    "name": "The Pretender",
    "duration": "268",
    "playcount": "201",
    "mbid": "fe10be03-5163-4410-ae77-05042a1d6ec8",
    "url": "http://www.last.fm/music/Foo+Fighters/_/The+Pretender",
    "streamable": {
        "#text": "0",
        "fulltrack": "0"
    },
    "artist": {
        "name": "Foo Fighters",
        "mbid": "67f66c07-6e61-4026-ade5-7e782fad3a5d",
        "url": "http://www.last.fm/music/Foo+Fighters"
    },
    "image": [
        {
            "#text": "http://userserve-ak.last.fm/serve/34s/83693587.png",
            "size": "small"
        },
        {
            "#text": "http://userserve-ak.last.fm/serve/64s/83693587.png",
            "size": "medium"
        },
        {
            "#text": "http://userserve-ak.last.fm/serve/126/83693587.png",
            "size": "large"
        },
        {
            "#text": "http://userserve-ak.last.fm/serve/300x300/83693587.png",
            "size": "extralarge"
        }
    ],
    "@attr": {
        "rank": "20"
    }
}, {
    "name": "Californication",
    "duration": "321",
    "playcount": "19",
    "mbid": "193f593a-3515-4232-bfc0-14f9f611e69d",
    "url": "http://www.last.fm/music/Red+Hot+Chili+Peppers/_/Californication",
    "streamable": {
        "#text": "0",
        "fulltrack": "0"
    },
    "artist": {
        "name": "Red Hot Chili Peppers",
        "mbid": "8bfac288-ccc5-448d-9573-c33ea2aa5c30",
        "url": "http://www.last.fm/music/Red+Hot+Chili+Peppers"
    },
    "image": [
        {
            "#text": "http://userserve-ak.last.fm/serve/34s/42739473.png",
            "size": "small"
        },
        {
            "#text": "http://userserve-ak.last.fm/serve/64s/42739473.png",
            "size": "medium"
        },
        {
            "#text": "http://userserve-ak.last.fm/serve/126/42739473.png",
            "size": "large"
        },
        {
            "#text": "http://userserve-ak.last.fm/serve/300x300/42739473.png",
            "size": "extralarge"
        }
    ],
    "@attr": {
        "rank": "33"
    }
}, {
    "name": "Hot n Cold",
    "duration": "221",
    "playcount": "193",
    "mbid": "075b7a97-0877-4c91-9d10-37d1b69876cc",
    "url": "http://www.last.fm/music/Katy+Perry/_/Hot+n+Cold",
    "streamable": {
        "#text": "0",
        "fulltrack": "0"
    },
    "artist": {
        "name": "Katy Perry",
        "mbid": "122d63fc-8671-43e4-9752-34e846d62a9c",
        "url": "http://www.last.fm/music/Katy+Perry"
    },
    "image": [
        {
            "#text": "http://userserve-ak.last.fm/serve/34s/92216597.png",
            "size": "small"
        },
        {
            "#text": "http://userserve-ak.last.fm/serve/64s/92216597.png",
            "size": "medium"
        },
        {
            "#text": "http://userserve-ak.last.fm/serve/126/92216597.png",
            "size": "large"
        },
        {
            "#text": "http://userserve-ak.last.fm/serve/300x300/92216597.png",
            "size": "extralarge"
        }
    ],
    "@attr": {
        "rank": "85"
    }
}, {
    "name": "Hotel California",
    "duration": "233",
    "playcount": "17",
    "mbid": "",
    "url": "http://www.last.fm/music/Los+Agues+(Fantasmas+Del+Romance)/_/Hotel+California",
    "streamable": {
        "#text": "0",
        "fulltrack": "0"
    },
    "artist": {
        "name": "Los Agues (Fantasmas Del Romance)",
        "mbid": "",
        "url": "http://www.last.fm/music/Los+Agues+(Fantasmas+Del+Romance)"
    },
    "@attr": {
        "rank": "49"
    }
}, {
    "name": "Billie Jean",
    "duration": "293",
    "playcount": "55",
    "mbid": "e9bda551-84a3-4b3e-8ada-55759de2475c",
    "url": "http://www.last.fm/music/Michael+Jackson/_/Billie+Jean",
    "streamable": {
        "#text": "0",
        "fulltrack": "0"
    },
    "artist": {
        "name": "Michael Jackson",
        "mbid": "210769a3-4aca-4199-a2e1-676ef376e078",
        "url": "http://www.last.fm/music/Michael+Jackson"
    },
    "image": [
        {
            "#text": "http://userserve-ak.last.fm/serve/34s/97977057.png",
            "size": "small"
        },
        {
            "#text": "http://userserve-ak.last.fm/serve/64s/97977057.png",
            "size": "medium"
        },
        {
            "#text": "http://userserve-ak.last.fm/serve/126/97977057.png",
            "size": "large"
        },
        {
            "#text": "http://userserve-ak.last.fm/serve/300x300/97977057.png",
            "size": "extralarge"
        }
    ],
    "@attr": {
        "rank": "45"
    }
}, {
    "name": "Get Lucky",
    "duration": "223",
    "playcount": "17",
    "mbid": "4c6efb4d-f5ee-4445-aa50-170caada2a1f",
    "url": "http://www.last.fm/music/New+Young+Pony+Club/_/Get+Lucky",
    "streamable": {
        "#text": "0",
        "fulltrack": "0"
    },
    "artist": {
        "name": "New Young Pony Club",
        "mbid": "61cd6f2a-cdde-4f34-aacd-b992badcacba",
        "url": "http://www.last.fm/music/New+Young+Pony+Club"
    },
    "image": [
        {
            "#text": "http://userserve-ak.last.fm/serve/34s/92617779.png",
            "size": "small"
        },
        {
            "#text": "http://userserve-ak.last.fm/serve/64s/92617779.png",
            "size": "medium"
        },
        {
            "#text": "http://userserve-ak.last.fm/serve/126/92617779.png",
            "size": "large"
        },
        {
            "#text": "http://userserve-ak.last.fm/serve/300x300/92617779.png",
            "size": "extralarge"
        }
    ],
    "@attr": {
        "rank": "72"
    }
}, {
    "name": "Rolling in the Deep",
    "duration": "228",
    "playcount": "162",
    "mbid": "092a88bc-af0b-4ddd-a3a1-17ad37abfccb",
    "url": "http://www.last.fm/music/Adele/_/Rolling+in+the+Deep",
    "streamable": {
        "#text": "0",
        "fulltrack": "0"
    },
    "artist": {
        "name": "Adele",
        "mbid": "1de93a63-3a9f-443a-ba8a-a43b5fe0121e",
        "url": "http://www.last.fm/music/Adele"
    },
    "image": [
        {
            "#text": "http://userserve-ak.last.fm/serve/34s/100102005.png",
            "size": "small"
        },
        {
            "#text": "http://userserve-ak.last.fm/serve/64s/100102005.png",
            "size": "medium"
        },
        {
            "#text": "http://userserve-ak.last.fm/serve/126/100102005.png",
            "size": "large"
        },
        {
            "#text": "http://userserve-ak.last.fm/serve/300x300/100102005.png",
            "size": "extralarge"
        }
    ],
    "@attr": {
        "rank": "8"
    }
}, {
    "name": "She Will Be Loved",
    "duration": "256",
    "playcount": "52",
    "mbid": "33ea05ca-4184-4ca8-969e-cb23582bcc2c",
    "url": "http://www.last.fm/music/Maroon+5/_/She+Will+Be+Loved",
    "streamable": {
        "#text": "0",
        "fulltrack": "0"
    },
    "artist": {
        "name": "Maroon 5",
        "mbid": "0ab49580-c84f-44d4-875f-d83760ea2cfe",
        "url": "http://www.last.fm/music/Maroon+5"
    },
    "image": [
        {
            "#text": "http://userserve-ak.last.fm/serve/34s/50461839.png",
            "size": "small"
        },
        {
            "#text": "http://userserve-ak.last.fm/serve/64s/50461839.png",
            "size": "medium"
        },
        {
            "#text": "http://userserve-ak.last.fm/serve/126/50461839.png",
            "size": "large"
        },
        {
            "#text": "http://userserve-ak.last.fm/serve/300x300/50461839.png",
            "size": "extralarge"
        }
    ],
    "@attr": {
        "rank": "45"
    }
}, {
    "name": "Boulevard of Broken Dreams",
    "duration": "260",
    "playcount": "61",
    "mbid": "043ae466-0c29-42f0-b511-50862c1c06ee",
    "url": "http://www.last.fm/music/Green+Day/_/Boulevard+of+Broken+Dreams",
    "streamable": {
        "#text": "0",
        "fulltrack": "0"
    },
    "artist": {
        "name": "Green Day",
        "mbid": "084308bd-1654-436f-ba03-df6697104e19",
        "url": "http://www.last.fm/music/Green+Day"
    },
    "image": [
        {
            "#text": "http://userserve-ak.last.fm/serve/34s/5083839.jpg",
            "size": "small"
        },
        {
            "#text": "http://userserve-ak.last.fm/serve/64s/5083839.jpg",
            "size": "medium"
        },
        {
            "#text": "http://userserve-ak.last.fm/serve/126/5083839.jpg",
            "size": "large"
        },
        {
            "#text": "http://userserve-ak.last.fm/serve/300x300/5083839.jpg",
            "size": "extralarge"
        }
    ],
    "@attr": {
        "rank": "20"
    }
}, {
    "name": "Bring Me to Life",
    "duration": "235",
    "playcount": "1",
    "mbid": "0bef462e-dff1-489f-982a-6ef2852bf65e",
    "url": "http://www.last.fm/music/Evanescence/_/Bring+Me+to+Life",
    "streamable": {
        "#text": "0",
        "fulltrack": "0"
    },
    "artist": {
        "name": "Evanescence",
        "mbid": "f4a31f0a-51dd-4fa7-986d-3095c40c5ed9",
        "url": "http://www.last.fm/music/Evanescence"
    },
    "image": [
        {
            "#text": "http://userserve-ak.last.fm/serve/34s/46370535.png",
            "size": "small"
        },
        {
            "#text": "http://userserve-ak.last.fm/serve/64s/46370535.png",
            "size": "medium"
        },
        {
            "#text": "http://userserve-ak.last.fm/serve/126/46370535.png",
            "size": "large"
        },
        {
            "#text": "http://userserve-ak.last.fm/serve/300x300/46370535.png",
            "size": "extralarge"
        }
    ],
    "@attr": {
        "rank": "25"
    }
}]
